cndi/__init__.py
cndi/consts.py
cndi/env.py
cndi/healthchecks.py
cndi/initializers.py
cndi/resources.py
cndi/utils.py
cndi/version.py
cndi/annotations/__init__.py
cndi/annotations/component.py
cndi/annotations/events.py
cndi/annotations/threads.py
cndi/autoconfiguration/__init__.py
cndi/autoconfiguration/configure.py
cndi/binders/__init__.py
cndi/binders/consts.py
cndi/binders/message/__init__.py
cndi/binders/message/mqtt.py
cndi/binders/message/rabbitmq.py
cndi/binders/message/s3.py
cndi/binders/message/utils.py
cndi/events/__init__.py
cndi/exception/__init__.py
cndi/flask/__init__.py
cndi/flask/flask_app.py
cndi/http/__init__.py
cndi/http/management/__init__.py
cndi/minio/__init__.py
cndi/rasa/__init__.py
cndi/rasa/configs.py
cndi/secrets/__init__.py
cndi/secrets/vault.py
cndi/validation/__init__.py
cndi-2.5.5.dist-info/licenses/LICENSE
tests/__init__.py
tests/test_load_envs.py
tests/cndi/__init__.py
tests/cndi/annotations/__init__.py
tests/cndi/annotations/test_app_initializer.py
tests/cndi/annotations/test_components.py
tests/cndi/binders/__init__.py
tests/cndi/binders/message/__init__.py
cndi-2.5.5.dist-info/METADATA
cndi-2.5.5.dist-info/WHEEL
cndi-2.5.5.dist-info/top_level.txt
cndi-2.5.5.dist-info/RECORD
